calculator_test/__init__.py
calculator_test/add.py
calculator_test/divide.py
calculator_test/multiply.py
calculator_test/subtract.py
calculater_test-0.0.1.dist-info/LICENSE
calculater_test-0.0.1.dist-info/METADATA
calculater_test-0.0.1.dist-info/WHEEL
calculater_test-0.0.1.dist-info/top_level.txt
calculater_test-0.0.1.dist-info/RECORD
