Metadata-Version: 2.1
Name: calculater_test
Version: 0.0.1
Summary: Test for use setuptools และ PyPI
Home-page: 
Author: Nantawan Chomboonmee
Author-email: nantawan@loolootech.com
Classifier: Programming Language :: Python :: 3
Classifier: License :: OSI Approved :: MIT License
Classifier: Operating System :: OS Independent
Requires-Python: >=3.6
License-File: LICENSE
